ml3m/__init__.py
ml3m/_async.py
ml3m/_color.py
ml3m/_display.py
ml3m/_docstring.py
ml3m/_emoji.py
ml3m/_logging.py
ml3m/_metrics.py
ml3m/_paths.py
ml3m/_typing.py
ml3m/_version.py
ml3m/errors.py
ml3m/base/__init__.py
ml3m/base/eval.py
ml3m/base/generate.py
ml3m/base/tests/__init__.py
ml3m/base/tests/test_eval.py
ml3m/base/tests/test_generate.py
ml3m/mcq/__init__.py
ml3m/mcq/eval.py
ml3m/qa/__init__.py
ml3m/qa/eval.py
ml3m/tests/__init__.py
ml3m/tests/test_async.py
ml3m/tests/test_docstring.py
ml3m/utils/__init__.py
ml3m/utils/openai.py
ml3m-0.0.20.dist-info/METADATA
ml3m-0.0.20.dist-info/WHEEL
ml3m-0.0.20.dist-info/top_level.txt
ml3m-0.0.20.dist-info/RECORD
