Metadata-Version: 2.1
Name: ml3m
Version: 0.0.20
Summary: Evaluting your LLM performance
Author: Charlie-XIAO (Yao Xiao)
Author-email: yx2436@nyu.edu
Keywords: python,LLM,evaluation
Classifier: Development Status :: 1 - Planning
Classifier: Intended Audience :: Developers
Classifier: Programming Language :: Python :: 3
Classifier: Operating System :: Microsoft :: Windows
Classifier: Operating System :: Unix
Classifier: Operating System :: MacOS :: MacOS X
Requires-Python: >=3.8
Requires-Dist: pandas
Requires-Dist: numpy
Requires-Dist: openai
Requires-Dist: tqdm
